{
  "date": "2025-06-09",
  "github_trending": [
    {
      "title": "microsoft/markitdown",
      "url": "https://github.com/microsoft/markitdown",
      "stars": 58833,
      "description": "Python tool for converting files and office documents to Markdown."
    },
    {
      "title": "DigitalPlatDev/FreeDomain",
      "url": "https://github.com/DigitalPlatDev/FreeDomain",
      "stars": 58665,
      "description": "DigitalPlat FreeDomain: Free Domain For Everyone"
    },
    {
      "title": "All-Hands-AI/OpenHands",
      "url": "https://github.com/All-Hands-AI/OpenHands",
      "stars": 57673,
      "description": "\ud83d\ude4c OpenHands: Code Less, Make More"
    },
    {
      "title": "punkpeye/awesome-mcp-servers",
      "url": "https://github.com/punkpeye/awesome-mcp-servers",
      "stars": 53934,
      "description": "A collection of MCP servers."
    },
    {
      "title": "xai-org/grok-1",
      "url": "https://github.com/xai-org/grok-1",
      "stars": 50301,
      "description": "Grok open release"
    }
  ],
  "hackernews_top": [
    {
      "title": "The New Godel Prize Winner Tastes Great and Is Less Filling",
      "url": "https://blog.computationalcomplexity.org/2025/06/the-new-godel-prize-winner-tastes-great.html",
      "score": 17
    },
    {
      "title": "Hokusai Moyo Gafu: an album of dyeing patterns",
      "url": "https://ndlsearch.ndl.go.jp/en/imagebank/theme/hokusaimoyo",
      "score": 11
    },
    {
      "title": "Why Quadratic Funding Is Not Optimal",
      "url": "https://jonathanwarden.com/quadratic-funding-is-not-optimal/",
      "score": 17
    },
    {
      "title": "Maypole Dance of Braid Like Groups",
      "url": "https://divisbyzero.com/2009/05/04/the-maypole-braid-group/",
      "score": 3
    },
    {
      "title": "Finding Shawn Mendes (2019)",
      "url": "https://ericneyman.wordpress.com/2019/11/26/finding-shawn-mendes/",
      "score": 247
    }
  ],
  "reddit_programming": [],
  "npm_trending": [
    {
      "name": "flatstr",
      "downloads": "N/A"
    },
    {
      "name": "mongoose",
      "downloads": "N/A"
    },
    {
      "name": "@vscode/web-custom-data",
      "downloads": "N/A"
    },
    {
      "name": "autoprefixer",
      "downloads": "N/A"
    },
    {
      "name": "storybook-source-link",
      "downloads": "N/A"
    }
  ],
  "pypi_trending": [
    {
      "name": "micro-liquid added to PyPI",
      "url": "https://pypi.org/project/micro-liquid/"
    },
    {
      "name": "pyfunmath added to PyPI",
      "url": "https://pypi.org/project/pyfunmath/"
    },
    {
      "name": "Priyansheda added to PyPI",
      "url": "https://pypi.org/project/priyansheda/"
    },
    {
      "name": "a-law-lib added to PyPI",
      "url": "https://pypi.org/project/a-law-lib/"
    },
    {
      "name": "tableswift added to PyPI",
      "url": "https://pypi.org/project/tableswift/"
    }
  ]
}